ahorcadozzz/__init__.py
ahorcadozzz/main.py
ahorcadozzz-1.1.dist-info/licenses/license.md
ahorcadozzz-1.1.dist-info/METADATA
ahorcadozzz-1.1.dist-info/WHEEL
ahorcadozzz-1.1.dist-info/top_level.txt
ahorcadozzz-1.1.dist-info/RECORD
