Metadata-Version: 2.4
Name: ahorcadoZzz
Version: 1.1
Summary: Ahorcado con palabras del mundo de la informática. ¡Sumérgete en el ahorcado más Zzz del universo!
Author: Christian Salguero
Requires-Python: >=3.8
License-File: license.md
Dynamic: license-file
